tadam/automaton.py
tadam/edge.py
tadam/mdl.py
tadam/options.py
tadam/state.py
tadam/tadam.py
tadam/talearner.py
tadam/ts.py
tadam/utils.py
tadam_learner-0.1.0.dist-info/licenses/LICENSE
tadam_learner-0.1.0.dist-info/METADATA
tadam_learner-0.1.0.dist-info/WHEEL
tadam_learner-0.1.0.dist-info/top_level.txt
tadam_learner-0.1.0.dist-info/RECORD
