Metadata-Version: 2.4
Name: tadam-learner
Version: 0.1.0
Summary: Probabilistic timed automata learner from noisy observations
Author: Lénaïg Cornanguer and Pierre-François Gimenez
License: BSD-3-Clause
License-File: LICENSE
Requires-Dist: numpy
Requires-Dist: scikit-learn
Requires-Dist: pandas
Dynamic: license-file
